iotadb/__init__.py
iotadb/iotadb.py
iotadb/metrics.py
iotadb/schemas.py
tests/__init__.py
iotadb-0.0.15.dist-info/LICENSE
iotadb-0.0.15.dist-info/METADATA
iotadb-0.0.15.dist-info/WHEEL
iotadb-0.0.15.dist-info/top_level.txt
iotadb-0.0.15.dist-info/RECORD
