Metadata-Version: 2.1
Name: iotadb
Version: 0.0.15
Summary: Minimal implementation of a local embedding database
Home-page: https://github.com/timothyckl/iota
Author: timothyckl
Author-email: timothy.ckl@outlook.com
License: MIT
Classifier: License :: OSI Approved :: MIT License
Classifier: Programming Language :: Python
Classifier: Operating System :: OS Independent
Requires-Python: >=3.8
License-File: LICENSE
Requires-Dist: numpy ==1.25.2
Requires-Dist: sentence-transformers ==2.6.1
Provides-Extra: dev
Requires-Dist: pytest ; extra == 'dev'
Requires-Dist: twine ; extra == 'dev'
